aio_crystal_pay/__init__.py
aio_crystal_pay/client.py
aio_crystal_pay/exceptions.py
tests/__init__.py
tests/test_aio_crystal_pay.py
aio_crystal_pay-1.0.5.dist-info/METADATA
aio_crystal_pay-1.0.5.dist-info/WHEEL
aio_crystal_pay-1.0.5.dist-info/top_level.txt
aio_crystal_pay-1.0.5.dist-info/RECORD
