Metadata-Version: 2.1
Name: aio-crystal-pay
Version: 1.0.5
Author: alteralt
Project-URL: Source, https://github.com/alteralt/aio_crystal_pay
Classifier: Development Status :: 5 - Production/Stable
Classifier: Intended Audience :: Developers
Classifier: Natural Language :: Russian
Classifier: Programming Language :: Python
Classifier: Programming Language :: Python :: 3.5
Classifier: Programming Language :: Python :: 3.6
Classifier: Programming Language :: Python :: 3.7
Classifier: Programming Language :: Python :: 3.8
Classifier: Programming Language :: Python :: 3.9
Classifier: Programming Language :: Python :: 3.10
Requires-Python: >=3.5
Requires-Dist: aiohttp (>=3.6.3)
